{
    "skills": {
        "1010701": {
            "tier": 1,
            "data": [
                {
                    "uptie": 1,
                    "affinity": "pride",
                    "atkType": "pierce",
                    "defType": "attack",
                    "atkWeight": 1,
                    "levelCorrection": 2,
                    "baseValue": 2,
                    "coinValue": 4,
                    "coinTypes": [
                        "normal",
                        "normal"
                    ]
                },
                {
                    "uptie": 2,
                    "coinValue": 4,
                    "coinTypes": [
                        "normal",
                        "normal"
                    ]
                },
                {
                    "uptie": 3,
                    "baseValue": 3
                },
                {
                    "uptie": 4,
                    "coinValue": 4,
                    "coinTypes": [
                        "normal",
                        "normal"
                    ]
                }
            ],
            "text": [
                {
                    "uptie": 1,
                    "name": "Impale",
                    "desc": "[WhenUse] Gain +2 [Breath] Count",
                    "coinDescs": [
                        [],
                        [
                            "[OnSucceedAttackHead] Inflict 2 [Laceration]"
                        ]
                    ]
                },
                {
                    "uptie": 2,
                    "name": "Impale",
                    "desc": "[WhenUse] Gain +2 [Breath] Count",
                    "coinDescs": [
                        [],
                        [
                            "[OnSucceedAttackHead] Inflict 1 [Binding] next turn",
                            "[OnSucceedAttack] Inflict 2 [Laceration]"
                        ]
                    ]
                },
                {
                    "uptie": 4,
                    "name": "Impale",
                    "desc": "[WhenUse] Gain +2 [Breath] Count",
                    "coinDescs": [
                        [],
                        [
                            "[OnSucceedAttack] Inflict 1 [Binding] next turn",
                            "[OnSucceedAttack] Inflict 2 [Laceration]"
                        ]
                    ]
                }
            ]
        },
        "1010702": {
            "tier": 2,
            "data": [
                {
                    "uptie": 1,
                    "affinity": "envy",
                    "atkType": "pierce",
                    "defType": "attack",
                    "atkWeight": 1,
                    "levelCorrection": 2,
                    "baseValue": 4,
                    "coinValue": 3,
                    "coinTypes": [
                        "normal",
                        "normal"
                    ]
                },
                {
                    "uptie": 2,
                    "coinValue": 3,
                    "coinTypes": [
                        "normal",
                        "normal"
                    ]
                },
                {
                    "uptie": 3,
                    "coinValue": 4,
                    "coinTypes": [
                        "normal",
                        "normal"
                    ]
                },
                {
                    "uptie": 4,
                    "coinValue": 4,
                    "coinTypes": [
                        "normal",
                        "normal"
                    ]
                }
            ],
            "text": [
                {
                    "uptie": 1,
                    "name": "Relentless Stabbing",
                    "desc": "[WhenUse] Gain +2 [Breath] Count\nAt 5+ [Breath], Clash Power +2",
                    "coinDescs": [
                        [
                            "[OnSucceedAttackHead] Gain 2 [Breath]"
                        ],
                        [
                            "[OnSucceedAttack] Inflict 1 [Laceration]"
                        ]
                    ]
                },
                {
                    "uptie": 2,
                    "name": "Relentless Stabbing",
                    "desc": "[WhenUse] Gain +2 [Breath] Count\nAt 5+ [Breath], Clash Power +2",
                    "coinDescs": [
                        [
                            "[OnSucceedAttackHead] Gain 2 [Breath]"
                        ],
                        [
                            "[OnSucceedAttack] Inflict 1 [Laceration]",
                            "[CriticalOnSucceedAttack] Reuse this Coin (1 time max)"
                        ]
                    ]
                },
                {
                    "uptie": 4,
                    "name": "Relentless Stabbing",
                    "desc": "[WhenUse] Gain +2 [Breath] Count\nAt 5+ [Breath], Clash Power +3",
                    "coinDescs": [
                        [
                            "[OnSucceedAttack] Gain 2 [Breath]"
                        ],
                        [
                            "[OnSucceedAttack] Inflict 1 [Laceration]",
                            "[CriticalOnSucceedAttack] Reuse this Coin (3 times max)"
                        ]
                    ]
                }
            ]
        },
        "1010703": {
            "tier": 3,
            "data": [
                {
                    "uptie": 3,
                    "affinity": "gluttony",
                    "atkType": "pierce",
                    "defType": "attack",
                    "atkWeight": 1,
                    "levelCorrection": 2,
                    "baseValue": 4,
                    "coinValue": 6,
                    "coinTypes": [
                        "normal",
                        "normal"
                    ]
                },
                {
                    "uptie": 4,
                    "coinValue": 6,
                    "coinTypes": [
                        "normal",
                        "normal"
                    ]
                }
            ],
            "text": [
                {
                    "uptie": 3,
                    "name": "Ambush",
                    "desc": "[WhenUse] Gain 5 [Breath]",
                    "coinDescs": [
                        [
                            "[OnSucceedAttackHead] Gain +2 [Breath] Count"
                        ],
                        [
                            "[OnSucceedAttack] Inflict 4 [Laceration]",
                            "[CriticalOnSucceedAttack] Inflict +4 [Laceration] Count"
                        ]
                    ]
                },
                {
                    "uptie": 4,
                    "name": "Ambush",
                    "desc": "[WhenUse] Gain 5 [Breath]\nAt 7+ [Breath], Coin Power +1",
                    "coinDescs": [
                        [
                            "[OnSucceedAttack] Gain +2 [Breath] Count"
                        ],
                        [
                            "[OnSucceedAttack] Inflict 4 [Laceration]",
                            "[CriticalOnSucceedAttack] Inflict +6 [Laceration] Count"
                        ]
                    ]
                }
            ]
        },
        "1010704": {
            "tier": 1,
            "data": [
                {
                    "uptie": 1,
                    "affinity": "none",
                    "atkType": null,
                    "defType": "evade",
                    "atkWeight": 1,
                    "levelCorrection": -3,
                    "baseValue": 2,
                    "coinValue": 10,
                    "coinTypes": [
                        "normal"
                    ]
                },
                {
                    "uptie": 4,
                    "affinity": "pride",
                    "baseValue": 3,
                    "coinValue": 10,
                    "coinTypes": [
                        "normal"
                    ]
                }
            ],
            "text": [
                {
                    "uptie": 1,
                    "name": "Evade",
                    "desc": "",
                    "coinDescs": [
                        [
                            ""
                        ]
                    ]
                },
                {
                    "uptie": 4,
                    "name": "Evade",
                    "desc": "",
                    "coinDescs": [
                        [
                            ""
                        ]
                    ]
                }
            ]
        }
    },
    "combatPassives": [
        {
            "level": 2,
            "passives": [
                1010701
            ]
        }
    ],
    "supportPassives": [
        {
            "level": 3,
            "passives": [
                1010721
            ]
        }
    ],
    "passiveData": {
        "1010721": {
            "name": "The First Mate's Acumen",
            "desc": "On Crit, 1 ally with the most [Breath] inflicts 2 additional [Laceration] Potency with a Skill (6 times per turn)",
            "condition": {
                "type": "owned",
                "requirement": [
                    {
                        "type": "pride",
                        "value": 4
                    }
                ]
            }
        },
        "1010701": {
            "name": "The First Mate's Harpoon",
            "desc": "On Crit, inflict 2 more [Laceration] Potency with a Skill (6 times per turn)",
            "condition": {
                "type": "owned",
                "requirement": [
                    {
                        "type": "pride",
                        "value": 4
                    }
                ]
            }
        }
    },
    "notes": {
        "short": "S2 can go up to 5 coins, but requires a lot of external {status:Breath} to be remotely consistent.",
        "full": "He reuses his 2nd coin on the S2 when he crits, but his {status:Breath} generation is extremely low, making it very inconsistent unless you have external support. He can inflict a lot of {status:Laceration} with it because of his passive if you can get it to work."
    }
}